ollehtv.py
ollehtv-0.1.2.dist-info/DESCRIPTION.rst
ollehtv-0.1.2.dist-info/METADATA
ollehtv-0.1.2.dist-info/RECORD
ollehtv-0.1.2.dist-info/WHEEL
ollehtv-0.1.2.dist-info/metadata.json
ollehtv-0.1.2.dist-info/top_level.txt
