Metadata-Version: 2.0
Name: ollehtv
Version: 0.1.2
Summary: Python library for controlling an Olleh TV STB
Home-page: https://github.com/pmrowla/ollehtv
Author: Peter Rowlands
Author-email: peter@pmrowla.com
License: MIT
Keywords: olleh ollehtv
Platform: UNKNOWN
Classifier: Development Status :: 3 - Alpha
Classifier: Intended Audience :: Developers
Classifier: Topic :: Software Development :: Libraries
Classifier: Topic :: Multimedia
Classifier: License :: OSI Approved :: MIT License
Classifier: Programming Language :: Python :: 2
Classifier: Programming Language :: Python :: 3
Requires-Dist: enum34
Requires-Dist: future
Requires-Dist: requests
